lson/__init__.py
lson/command_line.py
lson/lson.py
lson-1.1.1.dist-info/LICENSE
lson-1.1.1.dist-info/METADATA
lson-1.1.1.dist-info/WHEEL
lson-1.1.1.dist-info/entry_points.txt
lson-1.1.1.dist-info/top_level.txt
lson-1.1.1.dist-info/RECORD
