Metadata-Version: 2.1
Name: lson
Version: 1.1.1
Summary: Display directory structure in json format.
Home-page: UNKNOWN
Author: Alex Broaddus
Author-email: alexbroaddus1@gmail.com
License: UNKNOWN
Platform: UNKNOWN
Classifier: Programming Language :: Python :: 3
Classifier: License :: OSI Approved :: MIT License
Classifier: Operating System :: OS Independent
